furniture_bench/__init__.py
furniture_bench/config.py
furniture_bench/sim_config.py
furniture_bench/assets/__init__.py
furniture_bench/assets/calibration/__init__.py
furniture_bench/assets/calibration/cabinet.png
furniture_bench/assets/calibration/calibration.png
furniture_bench/assets/calibration/chair.png
furniture_bench/assets/calibration/desk.png
furniture_bench/assets/calibration/drawer.png
furniture_bench/assets/calibration/lamp.png
furniture_bench/assets/calibration/obstacle.png
furniture_bench/assets/calibration/one_leg.png
furniture_bench/assets/calibration/round_table.png
furniture_bench/assets/calibration/setup_front.png
furniture_bench/assets/calibration/square_table.png
furniture_bench/assets/calibration/stool.png
furniture_bench/assets/franka_description_ros/__init__.py
furniture_bench/assets/franka_description_ros/franka_description/CMakeLists.txt
furniture_bench/assets/franka_description_ros/franka_description/__init__.py
furniture_bench/assets/franka_description_ros/franka_description/mainpage.dox
furniture_bench/assets/franka_description_ros/franka_description/package.xml
furniture_bench/assets/franka_description_ros/franka_description/rosdoc.yaml
furniture_bench/assets/franka_description_ros/franka_description/meshes/__init__.py
furniture_bench/assets/franka_description_ros/franka_description/meshes/collision/__init__.py
furniture_bench/assets/franka_description_ros/franka_description/meshes/collision/hand.stl
furniture_bench/assets/franka_description_ros/franka_description/meshes/collision/link0.stl
furniture_bench/assets/franka_description_ros/franka_description/meshes/collision/link1.stl
furniture_bench/assets/franka_description_ros/franka_description/meshes/collision/link2.stl
furniture_bench/assets/franka_description_ros/franka_description/meshes/collision/link3.stl
furniture_bench/assets/franka_description_ros/franka_description/meshes/collision/link4.stl
furniture_bench-0.1.dist-info/LICENSE
furniture_bench-0.1.dist-info/METADATA
furniture_bench-0.1.dist-info/WHEEL
furniture_bench-0.1.dist-info/top_level.txt
furniture_bench-0.1.dist-info/RECORD
