Metadata-Version: 2.1
Name: furniture-bench
Version: 0.1
Summary: FurnitureBench: Reproducible Real-World Furniture Assembly Benchmark (RSS 2023)
Home-page: https://github.com/clvrai/furniture-bench
Author: CLVR @ KAIST
Author-email: clvr.kaist@gmail.com
Requires-Python: >=3.8
License-File: LICENSE
Requires-Dist: opencv-python
Requires-Dist: pynput
Requires-Dist: gym (==0.21.0)
Requires-Dist: joblib
Requires-Dist: numba
Requires-Dist: pyrealsense2
Requires-Dist: dt-apriltags
Requires-Dist: rich
Requires-Dist: tqdm
